sphinx_rtd_light_dark/__init__.py
sphinx_rtd_light_dark/breadcrumbs.html
sphinx_rtd_light_dark/layout.html
sphinx_rtd_light_dark/theme.conf
sphinx_rtd_light_dark/static/light-dark.css
sphinx_rtd_light_dark/static/light-dark.js
sphinx_rtd_light_dark-0.1.2.dist-info/METADATA
sphinx_rtd_light_dark-0.1.2.dist-info/WHEEL
sphinx_rtd_light_dark-0.1.2.dist-info/entry_points.txt
sphinx_rtd_light_dark-0.1.2.dist-info/top_level.txt
sphinx_rtd_light_dark-0.1.2.dist-info/RECORD
