Metadata-Version: 2.1
Name: sphinx-rtd-light-dark
Version: 0.1.2
Summary: A clean variant of the read the docs sphinx theme with light and dark modes.
Author: Luke Davis
Author-email: lukelbd@gmail.com
Maintainer: Luke Davis
Maintainer-email: lukelbd@gmail.com
License: MIT
Project-URL: Issue Tracker, https://github.com/lukelbd/sphinx_rtd_light_dark/issues
Project-URL: Source Code, https://github.com/lukelbd/sphinx_rtd_light_dark
Classifier: License :: OSI Approved :: MIT License
Classifier: Operating System :: OS Independent
Classifier: Intended Audience :: Developers
Classifier: Programming Language :: Python :: 3
Classifier: Programming Language :: Python :: 3.6
Classifier: Programming Language :: Python :: 3.7
Classifier: Programming Language :: Python :: 3.8
Classifier: Programming Language :: Python :: 3.9
Classifier: Programming Language :: Python :: 3.10
Requires-Python: >=3.6.0
Requires-Dist: pygments
Requires-Dist: sphinx-rtd-theme (==0.4.3)
